adaptivekde/__init__.py
adaptivekde/sshist.py
adaptivekde/sskernel.py
adaptivekde/ssvkernel.py
adaptivekde-1.1.0.dist-info/LICENSE.txt
adaptivekde-1.1.0.dist-info/METADATA
adaptivekde-1.1.0.dist-info/WHEEL
adaptivekde-1.1.0.dist-info/top_level.txt
adaptivekde-1.1.0.dist-info/RECORD
